eyeGestures/Fixation.py
eyeGestures/__init__.py
eyeGestures/calibration_v1.py
eyeGestures/calibration_v2.py
eyeGestures/eye.py
eyeGestures/face.py
eyeGestures/gazeContexter.py
eyeGestures/gazeEstimator.py
eyeGestures/gevent.py
eyeGestures/processing.py
eyeGestures/scalling_test.py
eyeGestures/screenTracker_test.py
eyeGestures/utils.py
eyeGestures/screenTracker/clusters.py
eyeGestures/screenTracker/dataPoints.py
eyeGestures/screenTracker/heatmap.py
eyeGestures/screenTracker/screenTracker.py
eyegestures-3.1.4.dist-info/METADATA
eyegestures-3.1.4.dist-info/WHEEL
eyegestures-3.1.4.dist-info/licenses/LICENSE
eyegestures-3.1.4.dist-info/RECORD
