Metadata-Version: 2.4
Name: eyeGestures
Version: 3.1.4
Summary: Package for eye tracking algorithm allowing for development of gaze controlled computer interface
Project-URL: Homepage, https://github.com/NativeSensors/EyeGestures
Project-URL: Issues, https://github.com/NativeSensors/EyeGestures/Issues
Author-email: Piotr Walas <piotr.walas@eyegestures.com>
Maintainer-email: Piotr Walas <piotr.walas@eyegestures.com>
License:                     GNU GENERAL PUBLIC LICENSE
License-File: LICENSE
Keywords: eye,eyetracking,gaze,gazetracking,tracking
Classifier: License :: OSI Approved :: GNU General Public License v3 (GPLv3)
Classifier: Operating System :: OS Independent
Classifier: Programming Language :: Python :: 3
Requires-Python: >=3.8
